rss2discord/__init__.py
rss2discord/__version__.py
rss2discord-0.3.3.dist-info/LICENSE
rss2discord-0.3.3.dist-info/METADATA
rss2discord-0.3.3.dist-info/WHEEL
rss2discord-0.3.3.dist-info/entry_points.txt
rss2discord-0.3.3.dist-info/RECORD
