Metadata-Version: 2.3
Name: rss2discord
Version: 0.3.3
Summary: A bot for feeding RSS feeds to Discord channels
Author: fluffy
Author-email: fluffy@beesbuzz.biz
Requires-Python: >=3.11
Classifier: Programming Language :: Python :: 3
Classifier: Programming Language :: Python :: 3.11
Classifier: Programming Language :: Python :: 3.12
Classifier: Programming Language :: Python :: 3.13
Requires-Dist: atomicwrites (>=1.4.1,<2.0.0)
Requires-Dist: beautifulsoup4 (>=4.13.4,<5.0.0)
Requires-Dist: feedparser (>=6.0.11,<7.0.0)
Requires-Dist: html-to-markdown (>=1.6.0,<2.0.0)
Requires-Dist: requests (>=2.32.4,<3.0.0)
Project-URL: Homepage, https://github.com/fluffy-critter/rss2discord
Project-URL: discord, https://beesbuzz.biz/discord
Project-URL: funding, https://ko-fi.com/fluffycritter
Project-URL: issues, https://github.com/fluffy-critter/rss2discord/issues
Project-URL: mastodon, https://plush.city/@fluffy
Project-URL: sponsor, https://github.com/sponsors/fluffy-critter
